gluellm/__init__.py
gluellm/api.py
gluellm/batch.py
gluellm/config.py
gluellm/embeddings.py
gluellm/schema.py
gluellm/telemetry.py
gluellm/agents/__init__.py
gluellm/agents/generic.py
gluellm/cli/__init__.py
gluellm/cli/utils.py
gluellm/cli/commands/__init__.py
gluellm/cli/commands/completion.py
gluellm/cli/commands/infrastructure.py
gluellm/cli/commands/tools.py
gluellm/cli/commands/utilities.py
gluellm/cli/commands/workflows.py
gluellm/costing/__init__.py
gluellm/costing/cost_tracker.py
gluellm/costing/pricing_data.py
gluellm/eval/__init__.py
gluellm/eval/callback_store.py
gluellm/eval/jsonl_store.py
gluellm/eval/multi_store.py
gluellm/eval/store.py
gluellm/executors/__init__.py
gluellm/executors/__main__.py
gluellm/executors/_base.py
gluellm/hooks/__init__.py
gluellm/hooks/manager.py
gluellm/hooks/utils.py
gluellm/models/__init__.py
gluellm/models/agent.py
gluellm/models/batch.py
gluellm/models/config.py
gluellm/models/conversation.py
gluellm/models/embedding.py
gluellm/models/eval.py
gluellm/models/hook.py
gluellm/models/prompt.py
gluellm/models/workflow.py
gluellm/observability/__init__.py
gluellm/observability/logging_config.py
gluellm/observability/logging_utils.py
gluellm/rate_limiting/__init__.py
gluellm/rate_limiting/api_key_pool.py
gluellm/rate_limiting/rate_limiter.py
gluellm/runtime/__init__.py
gluellm/runtime/context.py
gluellm/runtime/shutdown.py
gluellm/workflows/__init__.py
gluellm/workflows/_base.py
gluellm/workflows/chain_of_density.py
gluellm/workflows/chat_room.py
gluellm/workflows/consensus.py
gluellm/workflows/constitutional.py
gluellm/workflows/debate.py
gluellm/workflows/hierarchical.py
gluellm/workflows/iterative.py
gluellm/workflows/map_reduce.py
gluellm/workflows/mixture_of_experts.py
gluellm/workflows/pipeline.py
gluellm/workflows/rag.py
gluellm/workflows/react.py
gluellm/workflows/reflection.py
gluellm/workflows/round_robin.py
gluellm/workflows/socratic.py
gluellm/workflows/tree_of_thoughts.py
gluellm-1.1.2.dist-info/licenses/LICENSE
gluellm-1.1.2.dist-info/METADATA
gluellm-1.1.2.dist-info/WHEEL
gluellm-1.1.2.dist-info/entry_points.txt
gluellm-1.1.2.dist-info/top_level.txt
gluellm-1.1.2.dist-info/RECORD
