Metadata-Version: 2.4
Name: gluellm
Version: 1.1.2
Summary: A high-level Python SDK for Large Language Models with automatic tool execution, structured output support, multi-agent workflows, and evaluation data recording
Author-email: Nicholas Young <nick@nyoung.dev>
License: MIT
Project-URL: Homepage, https://github.com/Bioto/glue-llm
Project-URL: Documentation, https://github.com/Bioto/glue-llm#readme
Project-URL: Repository, https://github.com/Bioto/glue-llm
Project-URL: Issues, https://github.com/Bioto/glue-llm/issues
Keywords: llm,language-model,ai,openai,anthropic,claude,gpt,tool-calling,multi-agent,workflow,async
Classifier: Development Status :: 4 - Beta
Classifier: Intended Audience :: Developers
Classifier: License :: OSI Approved :: MIT License
Classifier: Operating System :: OS Independent
Classifier: Programming Language :: Python :: 3
Classifier: Programming Language :: Python :: 3.12
Classifier: Programming Language :: Python :: 3.13
Classifier: Topic :: Software Development :: Libraries :: Python Modules
Classifier: Topic :: Scientific/Engineering :: Artificial Intelligence
Requires-Python: >=3.12
License-File: LICENSE
Requires-Dist: any-llm-sdk[openai]>=1.5.0
Requires-Dist: click>=8.3.1
Requires-Dist: colorlog>=6.8.0
Requires-Dist: jinja2>=3.1.6
Requires-Dist: mlflow>=3.6.0
Requires-Dist: opentelemetry-api>=1.20.0
Requires-Dist: opentelemetry-sdk>=1.20.0
Requires-Dist: opentelemetry-exporter-otlp>=1.20.0
Requires-Dist: pydantic>=2.12.5
Requires-Dist: pydantic-settings>=2.12.0
Requires-Dist: python-json-logger>=2.0.7
Requires-Dist: pytest>=9.0.2
Requires-Dist: rich>=14.2.0
Requires-Dist: tenacity>=9.0.0
Requires-Dist: throttled-py>=3.1.0
Requires-Dist: aiofiles>=25.1.0
Provides-Extra: dev
Requires-Dist: pytest>=8.0.0; extra == "dev"
Requires-Dist: pytest-asyncio>=0.23.0; extra == "dev"
Dynamic: license-file
